tfx_addons/__init__.py
tfx_addons/version.py
tfx_addons/feast_examplegen/__init__.py
tfx_addons/feast_examplegen/component.py
tfx_addons/feast_examplegen/component_test.py
tfx_addons/feast_examplegen/converters.py
tfx_addons/feast_examplegen/executor.py
tfx_addons/feast_examplegen/executor_test.py
tfx_addons/feature_selection/__init__.py
tfx_addons/feature_selection/component.py
tfx_addons/feature_selection/component_test.py
tfx_addons/feature_selection/example/modules/iris_module_file.py
tfx_addons/feature_selection/example/modules/penguins_module.py
tfx_addons/feature_selection/example/modules/pima_indians_module_file.py
tfx_addons/firebase_publisher/__init__.py
tfx_addons/firebase_publisher/component.py
tfx_addons/firebase_publisher/component_test.py
tfx_addons/firebase_publisher/executor.py
tfx_addons/firebase_publisher/runner.py
tfx_addons/firebase_publisher/runner_test.py
tfx_addons/huggingface_pusher/__init__.py
tfx_addons/huggingface_pusher/component.py
tfx_addons/huggingface_pusher/component_test.py
tfx_addons/huggingface_pusher/executor.py
tfx_addons/huggingface_pusher/executor_test.py
tfx_addons/huggingface_pusher/runner.py
tfx_addons/huggingface_pusher/runner_test.py
tfx_addons/message_exit_handler/__init__.py
tfx_addons/message_exit_handler/component.py
tfx_addons/message_exit_handler/component_test.py
tfx_addons/message_exit_handler/constants.py
tfx_addons/message_exit_handler/message_providers/__init__.py
tfx_addons/message_exit_handler/message_providers/base_provider.py
tfx_addons/message_exit_handler/message_providers/base_provider_test.py
tfx_addons/message_exit_handler/message_providers/logging_provider.py
tfx_addons/message_exit_handler/message_providers/logging_provider_test.py
tfx_addons/message_exit_handler/message_providers/slack_provider.py
tfx_addons/message_exit_handler/message_providers/slack_provider_test.py
tfx_addons/mlmd_client/__init__.py
tfx_addons/mlmd_client/client.py
tfx_addons/mlmd_client/client_test.py
tfx_addons-0.6.0.dist-info/LICENSE
tfx_addons-0.6.0.dist-info/METADATA
tfx_addons-0.6.0.dist-info/WHEEL
tfx_addons-0.6.0.dist-info/top_level.txt
tfx_addons-0.6.0.dist-info/RECORD
