Metadata-Version: 2.1
Name: tfx-addons
Version: 0.6.0
Summary: TFX Addons libraries
Home-page: https://github.com/tensorflow/tfx-addons
Author: The Tensorflow Authors
Project-URL: Bug Tracker, https://github.com/tensorflow/tfx-addons/issues
Classifier: Intended Audience :: Developers
Classifier: Intended Audience :: Education
Classifier: Intended Audience :: Science/Research
Classifier: License :: OSI Approved :: Apache Software License
Classifier: Programming Language :: Python :: 3
Classifier: Programming Language :: Python :: 3.7
Classifier: Programming Language :: Python :: 3.8
Classifier: Programming Language :: Python :: 3.9
Classifier: Topic :: Scientific/Engineering
Classifier: Topic :: Scientific/Engineering :: Artificial Intelligence
Classifier: Topic :: Software Development
Classifier: Topic :: Software Development :: Libraries
Classifier: Topic :: Software Development :: Libraries :: Python Modules
Requires-Python: >=3.7
License-File: LICENSE
Provides-Extra: all
Requires-Dist: ml-metadata (<1.11.0,>=1.6.0) ; extra == 'all'
Requires-Dist: model-card-toolkit (<3.0.0,>=2.0.0) ; extra == 'all'
Requires-Dist: pydantic (<2.0,>=1.8.0) ; extra == 'all'
Requires-Dist: tfx (<1.11.0,>=1.6.0) ; extra == 'all'
Requires-Dist: slackclient (<3.0,>=2.9.0) ; extra == 'all'
Requires-Dist: firebase-admin (<6.0.0,>=5.0.0) ; extra == 'all'
Requires-Dist: feast (<0.23.0,>=0.21.3) ; extra == 'all'
Requires-Dist: scikit-learn (<2.0.0,>=1.0.2) ; extra == 'all'
Requires-Dist: huggingface-hub (<1.0.0,>=0.10.0) ; extra == 'all'
Requires-Dist: kfp (<2.0,>=1.8) ; extra == 'all'
Requires-Dist: xgboost (>=1.0.0) ; extra == 'all'
Requires-Dist: ml-pipelines-sdk (<1.11.0,>=1.6.0) ; extra == 'all'
Requires-Dist: pandas (<2.0,>=1.0.0) ; extra == 'all'
Requires-Dist: tensorflow (>=2.0.0) ; extra == 'all'
Provides-Extra: ci_max
Requires-Dist: tfx (~=1.10.0) ; extra == 'ci_max'
Requires-Dist: tensorflow (~=2.9.0) ; extra == 'ci_max'
Provides-Extra: ci_min
Requires-Dist: tfx (~=1.6.0) ; extra == 'ci_min'
Requires-Dist: tensorflow (~=2.8.0) ; extra == 'ci_min'
Provides-Extra: feast_examplegen
Requires-Dist: tfx (<1.11.0,>=1.6.0) ; extra == 'feast_examplegen'
Requires-Dist: feast (<0.23.0,>=0.21.3) ; extra == 'feast_examplegen'
Provides-Extra: feature_selection
Requires-Dist: tfx (<1.11.0,>=1.6.0) ; extra == 'feature_selection'
Requires-Dist: scikit-learn (<2.0.0,>=1.0.2) ; extra == 'feature_selection'
Provides-Extra: firebase_publisher
Requires-Dist: tfx (<1.11.0,>=1.6.0) ; extra == 'firebase_publisher'
Requires-Dist: firebase-admin (<6.0.0,>=5.0.0) ; extra == 'firebase_publisher'
Provides-Extra: huggingface_pusher
Requires-Dist: tfx (<1.11.0,>=1.6.0) ; extra == 'huggingface_pusher'
Requires-Dist: huggingface-hub (<1.0.0,>=0.10.0) ; extra == 'huggingface_pusher'
Provides-Extra: message_exit_handler
Requires-Dist: tfx (<1.11.0,>=1.6.0) ; extra == 'message_exit_handler'
Requires-Dist: kfp (<2.0,>=1.8) ; extra == 'message_exit_handler'
Requires-Dist: slackclient (<3.0,>=2.9.0) ; extra == 'message_exit_handler'
Requires-Dist: pydantic (<2.0,>=1.8.0) ; extra == 'message_exit_handler'
Provides-Extra: mlmd_client
Requires-Dist: ml-pipelines-sdk (<1.11.0,>=1.6.0) ; extra == 'mlmd_client'
Requires-Dist: ml-metadata (<1.11.0,>=1.6.0) ; extra == 'mlmd_client'
Provides-Extra: model_card_generator
Requires-Dist: tfx (<1.11.0,>=1.6.0) ; extra == 'model_card_generator'
Requires-Dist: model-card-toolkit (<3.0.0,>=2.0.0) ; extra == 'model_card_generator'
Provides-Extra: pandas_transform
Requires-Dist: tfx (<1.11.0,>=1.6.0) ; extra == 'pandas_transform'
Requires-Dist: pandas (<2.0,>=1.0.0) ; extra == 'pandas_transform'
Provides-Extra: sampling
Requires-Dist: tfx (<1.11.0,>=1.6.0) ; extra == 'sampling'
Requires-Dist: tensorflow (>=2.0.0) ; extra == 'sampling'
Provides-Extra: schema_curation
Requires-Dist: tfx (<1.11.0,>=1.6.0) ; extra == 'schema_curation'
Provides-Extra: test
Requires-Dist: pytest ; extra == 'test'
Requires-Dist: pylint ; extra == 'test'
Requires-Dist: pre-commit ; extra == 'test'
Requires-Dist: isort ; extra == 'test'
Requires-Dist: yapf ; extra == 'test'
Provides-Extra: xgboost_evaluator
Requires-Dist: tfx (<1.11.0,>=1.6.0) ; extra == 'xgboost_evaluator'
Requires-Dist: xgboost (>=1.0.0) ; extra == 'xgboost_evaluator'
